{"SE_T197_004": "205", "SE_T197_005": "252", "SE_T197_006": "17", "SE_T197_007": "0", "SE_T197_001": "555", "SE_T197_002": "7", "SE_T197_003": "74", "SE_T053_001": "2776", "Geo_ANRC": "", "SE_T053_002": "1944", "SE_T053_005": "184", "SE_T053_004": "224", "SE_T053_006": "8", "Geo_STATE": "41", "Geo_SDELM": "", "SE_T139_044": "0", "SE_T139_045": "0", "SE_T139_046": "0", "SE_T139_047": "0", "SE_T139_040": "26", "SE_T139_041": "21", "SE_T139_042": "0", "SE_T139_043": "0", "SE_T139_048": "0", "SE_T139_049": "0", "SE_T037_003": "245", "SE_T037_002": "2776", "SE_T037_001": "3021", "Geo_SDSEC": "", "SE_T128_008": "64", "SE_T128_009": "2194", "SE_T002_003": "1.029952648", "SE_T002_002": "5536.177", "SE_T002_001": "5702", "SE_T128_005": "16", "SE_T128_002": "2414", "SE_T128_003": "65", "SE_T128_001": "2650", "SE_T139_101": "191", "SE_T139_100": "245", "SE_T139_103": "39", "SE_T139_102": "0", "SE_T139_105": "0", "SE_T139_104": "15", "SE_T129_009": "49", "SE_T129_008": "136", "SE_T129_007": "361", "SE_T139_108": "0", "SE_T129_005": "617", "SE_T129_004": "503", "SE_T129_003": "395", "SE_T129_002": "2586", "SE_T129_001": "2650", "Geo_UGA": "", "Geo_PCI": "", "C16001028": "7", "C16001029": "0", "C16001022": "12", "C16001023": "0", "C16001020": "0", "C16001021": "12", "C16001026": "0", "SE_T053_003": "416", "C16001024": "0", "C16001025": "0", "SE_T133_004": "124", "SE_T133_005": "324", "SE_T133_002": "5254", "SE_T133_003": "448", "SE_T133_001": "5702", "Geo_PUMA1": "", "Geo_PUMA5": "", "SE_T219_005": "24", "Geo_FILEID": "ACSSF", "SE_T056_017": "5", "SE_T056_016": "36", "SE_T056_015": "95", "SE_T056_014": "197", "SE_T056_013": "378", "SE_T056_012": "259", "SE_T056_011": "227", "SE_T056_010": "38", "SE_T219_004": "52", "SE_T139_080": "0", "SE_T139_081": "0", "SE_T139_082": "0", "SE_T139_083": "0", "SE_T139_084": "0", "SE_T139_085": "0", "SE_T139_086": "0", "SE_T139_087": "0", "SE_T139_088": "0", "SE_T139_089": "0", "SE_T134_005": "145", "Geo_CDCURR": "", "SE_T139_039": "0", "SE_T139_038": "0", "SE_T139_035": "47", "SE_T139_034": "89", "SE_T139_037": "0", "SE_T139_036": "0", "SE_T139_031": "0", "SE_T139_030": "0", "SE_T139_033": "0", "SE_T139_032": "0", "Geo_NECTA": "", "Geo_DIVISION": "", "Geo_CSA": "", "SE_T007_008": "721", "SE_T007_009": "710", "SE_T007_006": "622", "SE_T007_007": "763", "SE_T007_004": "541", "SE_T007_005": "340", "SE_T007_002": "489", "SE_T007_003": "360", "SE_T007_001": "5702", "SE_T001_001": "5702", "Geo_CONCIT": "", "SE_T139_079": "0", "SE_T139_078": "0", "SE_T139_071": "0", "SE_T139_070": "0", "SE_T139_073": "0", "SE_T139_072": "0", "SE_T139_075": "0", "SE_T139_074": "0", "SE_T139_077": "0", "SE_T139_076": "0", "Geo_ZCTA5": "", "Geo_ZCTA3": "", "SE_T139_116": "0", "SE_T139_117": "0", "SE_T139_114": "0", "SE_T139_115": "0", "SE_T139_112": "14", "SE_T139_113": "0", "SE_T139_110": "0", "SE_T139_111": "0", "SE_T129_010": "64", "SE_T139_118": "0", "SE_T139_119": "0", "SE_T004_001": "5702", "SE_T134_004": "122", "SE_T004_003": "2948", "SE_T004_002": "2754", "SE_T134_001": "448", "SE_T134_003": "130", "SE_T134_002": "51", "Geo_BTBG": "", "C16001019": "12", "C16001018": "12", "C16001017": "0", "C16001016": "0", "C16001015": "0", "C16001014": "0", "C16001013": "0", "C16001012": "0", "C16001011": "0", "C16001010": "123", "SE_T050_011": "0", "SE_T050_010": "336", "SE_T050_013": "220", "SE_T050_012": "313", "SE_T050_014": "191", "Geo_COUNTY": "67", "Geo_SLDU": "", "Geo_BTTR": "", "SE_T128_006": "74", "Geo_SLDL": "", "SE_T128_007": "17", "SE_T128_004": "0", "SE_T083_001": "22705", "SE_T056_008": "126", "SE_T056_009": "104", "SE_T056_004": "91", "SE_T056_005": "97", "SE_T056_006": "110", "SE_T056_007": "77", "SE_T056_001": "1945", "SE_T056_002": "48", "SE_T056_003": "57", "SE_T139_107": "0", "SE_T139_106": "0", "SE_T139_109": "14", "SE_T129_006": "525", "Geo_CNECTA": "", "SE_T139_022": "0", "SE_T139_023": "0", "SE_T139_020": "0", "SE_T139_021": "0", "SE_T139_026": "0", "SE_T139_027": "0", "SE_T139_024": "0", "SE_T139_025": "0", "SE_T139_028": "0", "SE_T139_029": "0", "SE_T150_003": "2902", "SE_T150_002": "448", "SE_T150_001": "3350", "SE_T150_007": "81", "SE_T150_006": "322", "SE_T150_005": "798", "SE_T150_004": "1888", "SE_T150_008": "50", "Geo_AIANHHFP": "", "Geo_REGION": "", "SE_T139_122": "12", "SE_T139_121": "12", "SE_T139_120": "0", "Geo_PLACE": "", "Geo_TRACT": "33301", "Geo_UACP": "", "Geo_SDUNI": "", "Geo_GEOCOMP": "0", "Geo_NECTADIV": "", "Geo_STUSAB": "or", "SE_T003_002": "1.029953", "SE_T003_003": "0", "SE_T003_001": "1.029953", "Geo_PLACESE": "", "SE_T094_002": "1390", "SE_T094_003": "555", "SE_T094_001": "1945", "SE_T219_001": "555", "SE_T139_055": "5", "C16001027": "7", "SE_T219_002": "61", "SE_T139_068": "0", "SE_T139_069": "0", "SE_T139_066": "0", "SE_T139_067": "0", "SE_T139_064": "0", "SE_T139_065": "0", "SE_T139_062": "0", "SE_T139_063": "0", "SE_T139_060": "0", "SE_T139_061": "0", "SE_T139_051": "0", "SE_T219_006": "0", "SE_T139_019": "0", "SE_T139_018": "0", "SE_T139_013": "62", "SE_T139_012": "0", "SE_T139_011": "0", "SE_T139_010": "62", "SE_T139_017": "0", "SE_T139_016": "0", "SE_T139_015": "0", "SE_T139_014": "0", "Geo_AIANHH": "", "C16001001": "5213", "C16001002": "4458", "C16001003": "562", "C16001004": "327", "C16001005": "235", "C16001006": "0", "C16001007": "0", "C16001008": "0", "C16001009": "123", "SE_T050_006": "192", "SE_T050_007": "111", "SE_T050_004": "82", "SE_T050_005": "114", "SE_T050_002": "347", "SE_T050_003": "531", "Geo_STATECE": "", "SE_T050_001": "2776", "SE_T050_008": "135", "SE_T050_009": "204", "SE_T049_013": "107", "SE_T049_012": "233", "SE_T049_011": "641", "SE_T049_010": "154", "SE_T049_014": "128", "Geo_QName": "Census Tract 333.01, Washington County, Oregon", "Geo_US": "", "Geo_UR": "", "Geo_BLKGRP": "", "Geo_METDIV": "", "Geo_UA": "", "Geo_GEOID": "14000US41067033301", "Geo_MEMI": "", "Geo_AIHHTLI": "", "Geo_AITSCE": "", "Geo_LOGRECNO": "1739", "SE_T139_057": "0", "SE_T139_056": "0", "SE_T219_003": "418", "SE_T139_054": "37", "SE_T139_053": "0", "SE_T139_052": "0", "SE_T219_007": "0", "SE_T139_050": "42", "SE_T139_059": "0", "SE_T139_058": "0", "SE_T128_010": "220", "Geo_SUMLEV": "140", "Geo_FIPS": "41067033301", "C16001038": "0", "C16001031": "14", "C16001030": "26", "C16001033": "6", "C16001032": "12", "C16001035": "0", "C16001034": "6", "C16001037": "7", "Geo_VTD": "", "Geo_COUSUB": "", "Geo_AITS": "", "Geo_SUBMCD": "", "SE_T139_093": "0", "SE_T139_092": "0", "SE_T139_091": "259", "SE_T139_090": "271", "SE_T139_097": "0", "SE_T139_096": "0", "SE_T139_095": "0", "SE_T139_094": "0", "Geo_TAZ": "", "SE_T139_099": "0", "SE_T139_098": "0", "SE_T139_123": "0", "SE_T013_005": "185", "SE_T013_004": "0", "SE_T013_007": "29", "SE_T013_006": "0", "SE_T013_001": "5702", "Geo_CBSA": "", "SE_T013_003": "0", "SE_T013_002": "5065", "SE_T013_008": "423", "Geo_MACC": "", "C16001036": "7", "SE_T139_008": "0", "SE_T139_009": "0", "SE_T139_001": "448", "SE_T139_002": "88", "SE_T139_003": "26", "SE_T139_004": "26", "SE_T139_005": "0", "SE_T139_006": "26", "SE_T139_007": "0", "SE_T049_008": "52", "SE_T049_009": "155", "SE_T049_001": "2776", "SE_T049_002": "40", "SE_T049_003": "92", "SE_T049_004": "605", "SE_T049_005": "96", "SE_T049_006": "323", "SE_T049_007": "150", "Geo_NAME": "Census Tract 333.01, Washington County, Oregon", "SE_T007_011": "349", "SE_T007_010": "641", "SE_T007_013": "46", "SE_T007_012": "120"}